{
  "tasks": [
    {
      "text": "test task",
      "day": "anytime",
      "reminder": true,
      "id": 658
    },
    {
      "text": "TASK1",
      "day": "TODAY",
      "reminder": true,
      "id": 499
    },
    {
      "text": "Task2",
      "day": "This Evening",
      "reminder": true,
      "id": 615
    },
    {
      "text": "task3",
      "day": "anytime",
      "reminder": true,
      "id": 815
    },
    {
      "text": "new task",
      "day": "by 8pm, on Aug 2",
      "reminder": true,
      "id": 676
    }
  ]
}